Metadata-Version: 1.0
Name: pycobalt
Version: 0.0.2
Summary: AI module
Home-page: UNKNOWN
Author: SoftwareDebug
Author-email: zodiakraft@gmail.com
License: UNKNOWN
Platform: UNKNOWN
